Image2Story/__init__.py
Image2Story/class_caption.py
Image2Story/image2caption.py
Image2Story-0.0.6.dist-info/METADATA
Image2Story-0.0.6.dist-info/WHEEL
Image2Story-0.0.6.dist-info/top_level.txt
Image2Story-0.0.6.dist-info/RECORD
