Metadata-Version: 2.1
Name: Image2Story
Version: 0.0.6
Summary: Create Short Story from image caption
Home-page: https://github.com/falahgs/
Author: Falahgs.G.Saleih
Author-email: falahgs07@gmail.com
License: MIT
Keywords: CLIP,GPT3,BLIP
Classifier: Programming Language :: Python :: 3
Classifier: License :: OSI Approved :: MIT License
Classifier: Operating System :: OS Independent
Requires-Python: >=3.6
Requires-Dist: timm (==0.4.12)
Requires-Dist: fairscale (==0.4.4)
Requires-Dist: transformers
Requires-Dist: gitpython
Requires-Dist: pycocoevalcap
Requires-Dist: openai
Requires-Dist: googletrans (==3.1.0a0)
